ctftime_api/__init__.py
ctftime_api/client.py
ctftime_api/py.typed
ctftime_api/models/__init__.py
ctftime_api/models/country.py
ctftime_api/models/duration.py
ctftime_api/models/event.py
ctftime_api/models/rating.py
ctftime_api/models/team.py
ctftime_api/models/vote.py
ctftime_api-0.2.0.dist-info/METADATA
ctftime_api-0.2.0.dist-info/WHEEL
ctftime_api-0.2.0.dist-info/licenses/LICENSE
ctftime_api-0.2.0.dist-info/RECORD
