Metadata-Version: 2.4
Name: ctftime_api
Version: 0.2.0
Summary: CTFTime API wrapper
Project-URL: repository, https://github.com/jotonedev/ctftime_api
Project-URL: documentation, https://jotonedev.github.io/ctftime_api/
Author-email: John Toniutti <john.toniutti@gmail.com>
License-Expression: GPL-3.0-or-later
License-File: LICENSE
Keywords: api,ctftime,wrapper
Classifier: Development Status :: 4 - Beta
Classifier: Framework :: Pydantic
Classifier: Intended Audience :: Developers
Classifier: Operating System :: OS Independent
Classifier: Programming Language :: Python :: 3
Classifier: Programming Language :: Python :: 3.11
Classifier: Programming Language :: Python :: 3.12
Classifier: Programming Language :: Python :: 3.13
Classifier: Topic :: Internet :: WWW/HTTP
Classifier: Topic :: Software Development :: Libraries :: Python Modules
Classifier: Typing :: Typed
Requires-Python: >=3.11
Requires-Dist: dataclasses-json==0.6.7
Requires-Dist: httpx[http2]<0.29.0,>=0.28.1
Requires-Dist: yarl>=1.20.1
Provides-Extra: brotli
Requires-Dist: httpx[brotli]; extra == 'brotli'
Provides-Extra: zstd
Requires-Dist: httpx[zstd]; extra == 'zstd'
